WuaiPojieLuntanjinghuaJi2019DiwuBufen/README.md
WuaiPojieLuntanjinghuaJi2019DiwuBufen/__init__.py
WuaiPojieLuntanjinghuaJi2019DiwuBufen/__main__.py
WuaiPojieLuntanjinghuaJi2019DiwuBufen/file.epub
WuaiPojieLuntanjinghuaJi2019DiwuBufen/index.html
WuaiPojieLuntanjinghuaJi2019DiwuBufen/css/__init__.py
WuaiPojieLuntanjinghuaJi2019DiwuBufen/css/annotations.css
WuaiPojieLuntanjinghuaJi2019DiwuBufen/css/main.css
WuaiPojieLuntanjinghuaJi2019DiwuBufen/css/normalize.css
WuaiPojieLuntanjinghuaJi2019DiwuBufen/css/popup.css
WuaiPojieLuntanjinghuaJi2019DiwuBufen/font/__init__.py
WuaiPojieLuntanjinghuaJi2019DiwuBufen/font/fontello.eot
WuaiPojieLuntanjinghuaJi2019DiwuBufen/font/fontello.svg
WuaiPojieLuntanjinghuaJi2019DiwuBufen/font/fontello.ttf
WuaiPojieLuntanjinghuaJi2019DiwuBufen/font/fontello.woff
WuaiPojieLuntanjinghuaJi2019DiwuBufen/img/__init__.py
WuaiPojieLuntanjinghuaJi2019DiwuBufen/img/annotator-glyph-sprite.png
WuaiPojieLuntanjinghuaJi2019DiwuBufen/img/annotator-icon-sprite.png
WuaiPojieLuntanjinghuaJi2019DiwuBufen/img/apple-touch-icon.png
WuaiPojieLuntanjinghuaJi2019DiwuBufen/img/cancelfullscreen.png
WuaiPojieLuntanjinghuaJi2019DiwuBufen/img/close.png
WuaiPojieLuntanjinghuaJi2019DiwuBufen/img/fullscreen.png
WuaiPojieLuntanjinghuaJi2019DiwuBufen/img/loader.gif
WuaiPojieLuntanjinghuaJi2019DiwuBufen/img/menu-icon.png
WuaiPojieLuntanjinghuaJi2019DiwuBufen/img/save.png
WuaiPojieLuntanjinghuaJi2019DiwuBufen/img/saved.png
WuaiPojieLuntanjinghuaJi2019DiwuBufen/img/settings-s.png
WuaiPojieLuntanjinghuaJi2019DiwuBufen/img/settings.png
WuaiPojieLuntanjinghuaJi2019DiwuBufen/img/star.png
WuaiPojieLuntanjinghuaJi2019DiwuBufen/js/__init__.py
WuaiPojieLuntanjinghuaJi2019DiwuBufen/js/epub.js
WuaiPojieLuntanjinghuaJi2019DiwuBufen/js/epub.min.js
WuaiPojieLuntanjinghuaJi2019DiwuBufen/js/epub.min.map
WuaiPojieLuntanjinghuaJi2019DiwuBufen/js/hooks.min.js
WuaiPojieLuntanjinghuaJi2019DiwuBufen/js/hooks.min.map
WuaiPojieLuntanjinghuaJi2019DiwuBufen/js/reader.js
wuai_pojie_luntanjinghua_ji_2019_diwu_bufen-2024.3.5.0.dist-info/METADATA
wuai_pojie_luntanjinghua_ji_2019_diwu_bufen-2024.3.5.0.dist-info/WHEEL
wuai_pojie_luntanjinghua_ji_2019_diwu_bufen-2024.3.5.0.dist-info/entry_points.txt
wuai_pojie_luntanjinghua_ji_2019_diwu_bufen-2024.3.5.0.dist-info/top_level.txt
wuai_pojie_luntanjinghua_ji_2019_diwu_bufen-2024.3.5.0.dist-info/RECORD
